fastapi_pydentity/__init__.py
fastapi_pydentity/default_personal_data_protector.py
fastapi_pydentity/default_user_confirmation.py
fastapi_pydentity/exc.py
fastapi_pydentity/fastapi_identity.py
fastapi_pydentity/http_context.py
fastapi_pydentity/identity_error.py
fastapi_pydentity/identity_error_describer.py
fastapi_pydentity/identity_options.py
fastapi_pydentity/identity_result.py
fastapi_pydentity/lookup_normalizer.py
fastapi_pydentity/password_hasher.py
fastapi_pydentity/password_validator.py
fastapi_pydentity/rfc6238service.py
fastapi_pydentity/role_manager.py
fastapi_pydentity/role_validator.py
fastapi_pydentity/signin_manager.py
fastapi_pydentity/signin_result.py
fastapi_pydentity/token_provider.py
fastapi_pydentity/types.py
fastapi_pydentity/user_claims_principal_factory.py
fastapi_pydentity/user_login_info.py
fastapi_pydentity/user_manager.py
fastapi_pydentity/user_validator.py
fastapi_pydentity/abc/__init__.py
fastapi_pydentity/abc/lookup_normalizer.py
fastapi_pydentity/abc/password_hasher.py
fastapi_pydentity/abc/password_validator.py
fastapi_pydentity/abc/personal_data_protector.py
fastapi_pydentity/abc/role_validator.py
fastapi_pydentity/abc/token_provider.py
fastapi_pydentity/abc/user_claims_principal_factory.py
fastapi_pydentity/abc/user_confirmation.py
fastapi_pydentity/abc/user_validator.py
fastapi_pydentity/abc/stores/__init__.py
fastapi_pydentity/abc/stores/role_store.py
fastapi_pydentity/abc/stores/user_store.py
fastapi_pydentity/authentication/__init__.py
fastapi_pydentity/authentication/base.py
fastapi_pydentity/authentication/middleware.py
fastapi_pydentity/authentication/token_validation_parameters.py
fastapi_pydentity/authentication/bearer/__init__.py
fastapi_pydentity/authentication/bearer/backend.py
fastapi_pydentity/authentication/cookies/__init__.py
fastapi_pydentity/authentication/cookies/backend.py
fastapi_pydentity/authorization/__init__.py
fastapi_pydentity/authorization/authorization_provider.py
fastapi_pydentity-1.0.0.dist-info/LICENSE.txt
fastapi_pydentity-1.0.0.dist-info/METADATA
fastapi_pydentity-1.0.0.dist-info/WHEEL
fastapi_pydentity-1.0.0.dist-info/top_level.txt
fastapi_pydentity-1.0.0.dist-info/RECORD
